MANIFEST.in
README.md
setup.py
Flask_AdminLTE2.egg-info/PKG-INFO
Flask_AdminLTE2.egg-info/SOURCES.txt
Flask_AdminLTE2.egg-info/dependency_links.txt
Flask_AdminLTE2.egg-info/not-zip-safe
Flask_AdminLTE2.egg-info/requires.txt
Flask_AdminLTE2.egg-info/top_level.txt
flask_adminlte2/__init__.py
flask_adminlte2/static/css/AdminLTE.css
flask_adminlte2/static/css/AdminLTE.min.css
flask_adminlte2/static/css/bootstrap-theme.css
flask_adminlte2/static/css/bootstrap-theme.min.css
flask_adminlte2/static/css/bootstrap.css
flask_adminlte2/static/css/bootstrap.min.css
flask_adminlte2/static/css/style.css
flask_adminlte2/static/css/alt/AdminLTE-bootstrap-social.css
flask_adminlte2/static/css/alt/AdminLTE-bootstrap-social.min.css
flask_adminlte2/static/css/alt/AdminLTE-fullcalendar.css
flask_adminlte2/static/css/alt/AdminLTE-fullcalendar.min.css
flask_adminlte2/static/css/alt/AdminLTE-select2.css
flask_adminlte2/static/css/alt/AdminLTE-select2.min.css
flask_adminlte2/static/css/alt/AdminLTE-without-plugins.css
flask_adminlte2/static/css/alt/AdminLTE-without-plugins.min.css
flask_adminlte2/static/css/skins/_all-skins.css
flask_adminlte2/static/css/skins/_all-skins.min.css
flask_adminlte2/static/css/skins/skin-black-light.css
flask_adminlte2/static/css/skins/skin-black-light.min.css
flask_adminlte2/static/css/skins/skin-black.css
flask_adminlte2/static/css/skins/skin-black.min.css
flask_adminlte2/static/css/skins/skin-blue-light.css
flask_adminlte2/static/css/skins/skin-blue-light.min.css
flask_adminlte2/static/css/skins/skin-blue.css
flask_adminlte2/static/css/skins/skin-blue.min.css
flask_adminlte2/static/css/skins/skin-green-light.css
flask_adminlte2/static/css/skins/skin-green-light.min.css
flask_adminlte2/static/css/skins/skin-green.css
flask_adminlte2/static/css/skins/skin-green.min.css
flask_adminlte2/static/css/skins/skin-purple-light.css
flask_adminlte2/static/css/skins/skin-purple-light.min.css
flask_adminlte2/static/css/skins/skin-purple.css
flask_adminlte2/static/css/skins/skin-purple.min.css
flask_adminlte2/static/css/skins/skin-red-light.css
flask_adminlte2/static/css/skins/skin-red-light.min.css
flask_adminlte2/static/css/skins/skin-red.css
flask_adminlte2/static/css/skins/skin-red.min.css
