Metadata-Version: 2.1
Name: Flask-AdminLTE2
Version: 1.0.0
Summary: Integration of Flask-Admin and AdminLTE2 template.
Home-page: https://github.com/shijl0925/Flask-AdminLTE2
Author: Jialiang Shi
Author-email: kevin09254930sjl@gmail.com
License: MIT
Platform: any
Classifier: Environment :: Web Environment
Classifier: Intended Audience :: Developers
Classifier: License :: OSI Approved :: BSD License
Classifier: Operating System :: OS Independent
Classifier: Programming Language :: Python :: 3
Classifier: Topic :: Software Development :: Libraries :: Python Modules
